astrun/__init__.py
astrun/astrun.py
astrun/isolated_env.py
astrun-1.0.8.dist-info/LICENSE
astrun-1.0.8.dist-info/METADATA
astrun-1.0.8.dist-info/WHEEL
astrun-1.0.8.dist-info/top_level.txt
astrun-1.0.8.dist-info/RECORD
