Metadata-Version: 2.1
Name: astrun
Version: 1.0.8
Summary: A safe eval using Abstract Syntax Tree
Home-page: https://github.com/XiaoMutt/astrun
Author: Xiao
License: MIT
Classifier: License :: OSI Approved :: MIT License
Classifier: Programming Language :: Python :: 3.11
Classifier: Programming Language :: Python :: 3.12
Classifier: Programming Language :: Python :: 3 :: Only
License-File: LICENSE
